wadebug/__init__.py
wadebug/analytics.py
wadebug/cli.py
wadebug/cli_param.py
wadebug/cli_reusable_params.py
wadebug/cli_utils.py
wadebug/config.py
wadebug/exceptions.py
wadebug/results.py
wadebug/ui.py
wadebug/wadebug.conf.yml.SAMPLE
wadebug/tests/__init__.py
wadebug/tests/conftest.py
wadebug/tests/test_analytics.py
wadebug/tests/test_cli.py
wadebug/tests/test_cli_utils.py
wadebug/tests/test_config.py
wadebug/tests/test_crash_logs.py
wadebug/tests/test_ui.py
wadebug/wa_actions/__init__.py
wadebug/wa_actions/base.py
wadebug/wa_actions/curl_utils.py
wadebug/wa_actions/docker_utils.py
wadebug/wa_actions/log_utils.py
wadebug/wa_actions/mysql_utils.py
wadebug/wa_actions/network_utils.py
wadebug/wa_actions/test_curl_utils.py
wadebug/wa_actions/test_docker_utils.py
wadebug/wa_actions/test_log_utils.py
wadebug/wa_actions/test_mysql_utils.py
wadebug/wa_actions/test_network_utils.py
wadebug/wa_actions/test_wabiz_api.py
wadebug/wa_actions/wabiz_api.py
wadebug/wa_actions/common/__init__.py
wadebug/wa_actions/common/common_results.py
wadebug/wa_actions/implementations/__init__.py
wadebug/wa_actions/implementations/check_containers.py
wadebug/wa_actions/implementations/check_db_settings_exist.py
wadebug/wa_actions/implementations/check_mysql_connection.py
wadebug/wa_actions/implementations/check_mysql_password.py
wadebug/wa_actions/implementations/check_mysql_permissions.py
wadebug/wa_actions/implementations/check_mysql_version.py
wadebug/wa_actions/implementations/check_network.py
wadebug/wa_actions/implementations/check_software_version.py
wadebug/wa_actions/implementations/check_webapp_port.py
wadebug/wa_actions/implementations/check_webhook.py
wadebug/wa_actions/implementations/dummy_action.py
wadebug/wa_actions/tests/__init__.py
wadebug/wa_actions/tests/test_actions_module.py
wadebug/wa_actions/tests/test_check_mysql_connection.py
wadebug/wa_actions/tests/test_check_mysql_permissions.py
wadebug/wa_actions/tests/test_check_network.py
wadebug-0.1.5.dist-info/LICENSE
wadebug-0.1.5.dist-info/METADATA
wadebug-0.1.5.dist-info/WHEEL
wadebug-0.1.5.dist-info/entry_points.txt
wadebug-0.1.5.dist-info/top_level.txt
wadebug-0.1.5.dist-info/RECORD
