Metadata-Version: 2.1
Name: wadebug
Version: 0.1.5
Summary: Investigate issues with WhatsApp Business API setup.
Home-page: https://developers.facebook.com/docs/whatsapp/guides/wadebug
Author: Thiago Moraes
Author-email: tmoraes@fb.com
License: MIT
Platform: any
Classifier: Development Status :: 3 - Alpha
Classifier: Environment :: Console
Classifier: Intended Audience :: Developers
Classifier: License :: OSI Approved :: MIT License
Classifier: Operating System :: POSIX
Classifier: Operating System :: MacOS
Classifier: Operating System :: Unix
Classifier: Operating System :: Microsoft :: Windows
Classifier: Programming Language :: Python
Classifier: Programming Language :: Python :: 2
Classifier: Programming Language :: Python :: 3
Classifier: Topic :: Software Development :: Libraries :: Python Modules
Requires-Dist: click
Requires-Dist: docker
Requires-Dist: outdated
Requires-Dist: pydash
Requires-Dist: PyMySQL
Requires-Dist: pytest
Requires-Dist: pytest-cov
Requires-Dist: PyYAML
Requires-Dist: six
Requires-Dist: mock
Requires-Dist: enum34 ; python_version < "3.4"
